Metadata-Version: 2.1
Name: stringsfuns
Version: 0.1
Summary: String functions
Home-page: UNKNOWN
Author: Thorati Jai Satya Sai Phanindra
Author-email: thoratiphanindra@gmail.com
License: UNKNOWN
Platform: UNKNOWN
Classifier: Programming Language :: Python :: 3
Classifier: License :: OSI Approved :: MIT License
Classifier: Operating System :: OS Independent
Requires-Python: >=3.6
